yaecs/__init__.py
yaecs/_version.py
yaecs/config_history.py
yaecs/user_utils.py
yaecs/yaecs_utils.py
yaecs/config/__init__.py
yaecs/config/config.py
yaecs/config/config_base.py
yaecs/config/config_convenience.py
yaecs/config/config_getters.py
yaecs/config/config_hooks.py
yaecs/config/config_processing_functions.py
yaecs/config/config_setters.py
yaecs/config/setter.py
yaecs/config/yaml_scanner.py
yaecs/experiment/__init__.py
yaecs/experiment/experiment.py
yaecs/experiment/experiment_utils.py
yaecs/experiment/pytorch_lightning_utils.py
yaecs/experiment/timer.py
yaecs/experiment/tracker.py
yaecs/experiment/loggers/__init__.py
yaecs/experiment/loggers/aggregate_logger.py
yaecs/experiment/loggers/base_logger.py
yaecs/experiment/loggers/logger_basic.py
yaecs/experiment/loggers/logger_clearml.py
yaecs/experiment/loggers/logger_mlflow.py
yaecs/experiment/loggers/logger_sacred.py
yaecs/experiment/loggers/logger_tensorboard.py
yaecs/experiment/loggers/logger_utils.py
yaecs-7.1.2.dist-info/licenses/COPYING.LESSER.md
yaecs-7.1.2.dist-info/licenses/COPYING.md
yaecs-7.1.2.dist-info/licenses/LICENSE.md
yaecs-7.1.2.dist-info/METADATA
yaecs-7.1.2.dist-info/WHEEL
yaecs-7.1.2.dist-info/top_level.txt
yaecs-7.1.2.dist-info/RECORD
