Metadata-Version: 2.4
Name: yaecs
Version: 7.1.2
Summary: A Config System designed for experimental purposes
Author: Reactive Reality AG
Project-URL: Source, https://gitlab.com/reactivereality/public/yaecs
Keywords: template,machine,learning
Classifier: Programming Language :: Python :: 3
Requires-Python: >=3.6
License-File: LICENSE.md
License-File: COPYING.LESSER.md
License-File: COPYING.md
Requires-Dist: pyyaml<7,>=6
Requires-Dist: mock==4.0.3
Dynamic: license-file
